README.md
pyproject.toml
flockr/__init__.py
flockr.egg-info/PKG-INFO
flockr.egg-info/SOURCES.txt
flockr.egg-info/dependency_links.txt
flockr.egg-info/top_level.txt